guitar_scale_generator/__init__.py
guitar_scale_generator/guitar_scale_generator.py
guitar_scale_generator-0.1.0.dist-info/LICENSE
guitar_scale_generator-0.1.0.dist-info/METADATA
guitar_scale_generator-0.1.0.dist-info/WHEEL
guitar_scale_generator-0.1.0.dist-info/top_level.txt
guitar_scale_generator-0.1.0.dist-info/RECORD
