Metadata-Version: 2.1
Name: guitar-scale-generator
Version: 0.1.0
Summary: Generate an image of a fretboard with a user selected key, scale and number of string.
Home-page: https://github.com/alexlewzey/guitar_scale_generator
Author: Alexander Lewzey
Author-email: a.lewzey@hotmail.co.uk
License: BSD license
Keywords: guitar_scale_generator
Platform: UNKNOWN
Classifier: Development Status :: 2 - Pre-Alpha
Classifier: Intended Audience :: Developers
Classifier: License :: OSI Approved :: BSD License
Classifier: Natural Language :: English
Classifier: Programming Language :: Python :: 3
Classifier: Programming Language :: Python :: 3.5
Classifier: Programming Language :: Python :: 3.6
Classifier: Programming Language :: Python :: 3.7
Classifier: Programming Language :: Python :: 3.8
Requires-Python: >=3.5
